dagster_odp/__init__.py
dagster_odp/utils.py
dagster_odp/config_manager/__init__.py
dagster_odp/config_manager/builders/__init__.py
dagster_odp/config_manager/builders/base_builder.py
dagster_odp/config_manager/builders/config_builder.py
dagster_odp/config_manager/builders/workflow_builder.py
dagster_odp/config_manager/models/__init__.py
dagster_odp/config_manager/models/config_model.py
dagster_odp/config_manager/models/workflow_model.py
dagster_odp/creators/__init__.py
dagster_odp/creators/asset_check_creator.py
dagster_odp/creators/job_creator.py
dagster_odp/creators/schedule_creator.py
dagster_odp/creators/sensor_creator.py
dagster_odp/creators/asset_creators/__init__.py
dagster_odp/creators/asset_creators/base_asset_creator.py
dagster_odp/creators/asset_creators/dbt_asset_creator.py
dagster_odp/creators/asset_creators/dlt_asset_creator.py
dagster_odp/creators/asset_creators/generic_asset_creator.py
dagster_odp/creators/asset_creators/utils.py
dagster_odp/resources/__init__.py
dagster_odp/resources/resource_registry.py
dagster_odp/resources/definitions/__init__.py
dagster_odp/resources/definitions/dlt_resource.py
dagster_odp/resources/definitions/duckdb_resource.py
dagster_odp/resources/definitions/soda_resource.py
dagster_odp/resources/definitions/utils.py
dagster_odp/sensors/__init__.py
dagster_odp/sensors/definitions/__init__.py
dagster_odp/sensors/definitions/gcs_sensor.py
dagster_odp/sensors/manager/__init__.py
dagster_odp/sensors/manager/base_sensor.py
dagster_odp/sensors/manager/sensor_registry.py
dagster_odp/tasks/__init__.py
dagster_odp/tasks/utils.py
dagster_odp/tasks/definitions/__init__.py
dagster_odp/tasks/definitions/duckdb_tasks.py
dagster_odp/tasks/definitions/gcp_tasks.py
dagster_odp/tasks/definitions/util_tasks.py
dagster_odp/tasks/manager/__init__.py
dagster_odp/tasks/manager/base_task.py
dagster_odp/tasks/manager/task_registry.py
dagster_odp-0.1.4.dist-info/LICENSE
dagster_odp-0.1.4.dist-info/METADATA
dagster_odp-0.1.4.dist-info/WHEEL
dagster_odp-0.1.4.dist-info/top_level.txt
dagster_odp-0.1.4.dist-info/RECORD
