Metadata-Version: 2.1
Name: dagster-odp
Version: 0.1.4
Summary: A configuration-driven framework for building Dagster pipelines
Author-email: Jonathan Bhaskar <hello@jonathanb.me>
Classifier: Programming Language :: Python :: 3
Classifier: Programming Language :: Python :: 3.9
Classifier: Programming Language :: Python :: 3.10
Classifier: Programming Language :: Python :: 3.11
Classifier: Programming Language :: Python :: 3.12
Classifier: License :: OSI Approved :: Apache Software License
Classifier: Development Status :: 4 - Beta
Classifier: Intended Audience :: Developers
Classifier: Topic :: Software Development :: Libraries :: Python Modules
Classifier: Topic :: Software Development :: Libraries :: Application Frameworks
Requires-Python: <3.13,>=3.9
License-File: LICENSE
Requires-Dist: dagster <1.10.0,>=1.9.1
Requires-Dist: dagster-webserver <1.10.0,>=1.9.1
Requires-Dist: dagster-gcp <0.26.0,>=0.25.1
Requires-Dist: dagster-dbt <0.26.0,>=0.25.1
Requires-Dist: dbt-core <1.9.0,>=1.8.8
Requires-Dist: dbt-bigquery <1.9.0,>=1.8.3
Requires-Dist: dbt-duckdb <1.9.0,>=1.8.4
Requires-Dist: dlt[bigquery] <0.6.0,>=0.5.4
Requires-Dist: duckdb <2.0.0,>=1.0.0
Requires-Dist: google-cloud-storage <3.0.0,>=2.18.2
Requires-Dist: fsspec >=2024.10.0
Requires-Dist: gcsfs >=2024.10.0
Requires-Dist: soda-core <3.4.0,>=3.3.22
Requires-Dist: soda-core-bigquery <3.4.0,>=3.3.22
Requires-Dist: soda-core-duckdb <3.4.0,>=3.3.22
Requires-Dist: chevron <0.15.0,>=0.14.0
Requires-Dist: requests <3.0.0,>=2.32.3
Provides-Extra: dev
Requires-Dist: pytest <9.0.0,>=8.3.3 ; extra == 'dev'
Requires-Dist: freezegun <2.0.0,>=1.5.1 ; extra == 'dev'
Requires-Dist: pytest-cov >=6.0.0 ; extra == 'dev'
Requires-Dist: mkdocs-material <10.0.0,>=9.5.44 ; extra == 'dev'
Requires-Dist: mkdocs-glightbox <0.5.0,>=0.4.0 ; extra == 'dev'
Requires-Dist: black >=24.10.0 ; extra == 'dev'
Requires-Dist: flake8 >=7.1.1 ; extra == 'dev'
Requires-Dist: flake8-bugbear >=24.10.31 ; extra == 'dev'
Requires-Dist: isort >=5.13.2 ; extra == 'dev'
Requires-Dist: mypy >=1.13.0 ; extra == 'dev'
Requires-Dist: pylint >=3.3.1 ; extra == 'dev'
